s3recon/__init__.py
s3recon/__main__.py
s3recon/constants.py
s3recon/mongodb.py
s3recon/s3recon.py
s3recon/s3recon.yml
s3recon-1.4.0.dist-info/LICENSE
s3recon-1.4.0.dist-info/METADATA
s3recon-1.4.0.dist-info/WHEEL
s3recon-1.4.0.dist-info/entry_points.txt
s3recon-1.4.0.dist-info/top_level.txt
s3recon-1.4.0.dist-info/RECORD
