Metadata-Version: 2.1
Name: s3recon
Version: 1.4.0
Summary: Amazon S3 bucket finder.
Home-page: https://github.com/clarketm/s3recon
Author: Travis Clarke
Author-email: travis.m.clarke@gmail.com
License: UNKNOWN
Platform: UNKNOWN
Classifier: Programming Language :: Python :: 3
Classifier: Programming Language :: Python :: 3.6
Classifier: Programming Language :: Python :: 3.7
Classifier: Programming Language :: Python :: 3.8
Classifier: License :: OSI Approved :: MIT License
Classifier: Operating System :: OS Independent
Requires-Python: >=3.6
Requires-Dist: mergedeep (>=1.1)
Requires-Dist: requests (>=2.23)
Requires-Dist: pymongo (>=3.10)
Requires-Dist: pyyaml (>=5.3)
